Metadata-Version: 1.0
Name: mass-production
Version: 1.0.2
Summary: Call a function (e.g a factory-boy Factory's create method) according to a defined pattern.
Home-page: http://github.com/RobinRamael/mass-production
Author: Robin Ramael
Author-email: robin.ramael@gmail.com
License: MIT
Platform: UNKNOWN
